icicle_playgrounds/__init__.py
icicle_playgrounds/pydantic/__init__.py
icicle_playgrounds/pydantic/patra_model_cards/PatraAIModel.py
icicle_playgrounds/pydantic/patra_model_cards/PatraBiasAnalysis.py
icicle_playgrounds/pydantic/patra_model_cards/PatraModelCard.py
icicle_playgrounds/pydantic/patra_model_cards/PatraXAIAnalysis.py
icicle_playgrounds/pydantic/patra_model_cards/__init__.py
icicle_playgrounds/pydantic/plug_n_play/DetectionResults.py
icicle_playgrounds/pydantic/plug_n_play/Image.py
icicle_playgrounds/pydantic/plug_n_play/Tensor.py
icicle_playgrounds/pydantic/plug_n_play/__init__.py
icicle_playgrounds-0.1.5.6.dist-info/licenses/LICENSE
icicle_playgrounds-0.1.5.6.dist-info/METADATA
icicle_playgrounds-0.1.5.6.dist-info/WHEEL
icicle_playgrounds-0.1.5.6.dist-info/top_level.txt
icicle_playgrounds-0.1.5.6.dist-info/RECORD
