Metadata-Version: 2.4
Name: icicle-playgrounds
Version: 0.1.5.6
Summary: SDK to interact with the ICICLE Model & Data Playgrounds
Requires-Python: >=3.10
License-File: LICENSE
Requires-Dist: httpx>=0.28.1
Requires-Dist: pillow>=11.2.1
Requires-Dist: pydantic>=2.11.7
Requires-Dist: torchvision>=0.22.1
Dynamic: license-file
